mongoql_conv-0.4.1.dist-info/RECORD
mongoql_conv-0.4.1.dist-info/top_level.txt
mongoql_conv-0.4.1.dist-info/DESCRIPTION.rst
mongoql_conv-0.4.1.dist-info/METADATA
mongoql_conv-0.4.1.dist-info/pydist.json
mongoql_conv-0.4.1.dist-info/WHEEL
mongoql_conv/__init__.py
mongoql_conv/django.py
