Metadata-Version: 2.0
Name: mongoql-conv
Version: 0.4.1
Summary: Library to convert those MongoDB queries to something else, like a python expresion, a function or a Django Q object tree to be used with a ORM query.
Home-page: https://github.com/ionelmc/python-mongoql-conv
Author: Ionel Cristian Mărieș
Author-email: contact@ionelmc.ro
License: BSD
Keywords: mongo,mongodb,django,orm,query,conversion,converter
Platform: UNKNOWN
Classifier: Development Status :: 4 - Beta
Classifier: Intended Audience :: Developers
Classifier: License :: OSI Approved :: BSD License
Classifier: Operating System :: Unix
Classifier: Operating System :: POSIX
Classifier: Programming Language :: Python
Classifier: Topic :: Software Development :: Debuggers
Classifier: Topic :: Utilities
Classifier: Programming Language :: Python :: 2.7
Classifier: Programming Language :: Python :: 3
Classifier: Programming Language :: Python :: 3.2
Classifier: Programming Language :: Python :: 3.3
Classifier: Programming Language :: Python :: Implementation :: CPython
Classifier: Programming Language :: Python :: Implementation :: PyPy
Requires-Dist: six
Provides-Extra: django
Requires-Dist: Django; extra == 'django'
